dnull_mqtt/__init__.py
dnull_mqtt/apps/__init__.py
dnull_mqtt/apps/app.py
dnull_mqtt/apps/binance.py
dnull_mqtt/apps/budget.py
dnull_mqtt/apps/notion.py
dnull_mqtt/apps/nutrition.py
dnull_mqtt/awtrix.py
dnull_mqtt/base_log.py
dnull_mqtt/colors.py
dnull_mqtt/config.py
dnull_mqtt/main.py
dnull_mqtt/mqtt.py
dnullproject_iot-0.4.0.dist-info/METADATA
dnullproject_iot-0.4.0.dist-info/WHEEL
dnullproject_iot-0.4.0.dist-info/entry_points.txt
dnullproject_iot-0.4.0.dist-info/RECORD
