Metadata-Version: 2.1
Name: dnullproject-iot
Version: 0.4.0
Summary: 0.1.0
Author: Bohdan Sukhomlinov
Author-email: shellshock1953@gmail.com
Requires-Python: >=3.10,<4.0
Classifier: Programming Language :: Python :: 3
Classifier: Programming Language :: Python :: 3.10
Classifier: Programming Language :: Python :: 3.11
Classifier: Programming Language :: Python :: 3.12
Requires-Dist: binance-connector (>=3.5.1,<4.0.0)
Requires-Dist: fatsecret (>=0.4.0,<0.5.0)
Requires-Dist: notion-client (>=2.1.0,<3.0.0)
Requires-Dist: paho-mqtt (>=1.6.1,<2.0.0)
